<?xml version="1.0"?>
<taskFile>
	<question>
		<input>fdafea</input>
		<input>dcae</input>
		<taskoptions></taskoptions>
		<answer>yes</answer>
	</question>
	<question>
		<input>daee</input>
		<input>dsads2</input>
		<taskoptions></taskoptions>
		<answer>no</answer>
	</question>
	<question>
		<input>adfae</input>
		<input>wdsad</input>
		<taskoptions></taskoptions>
		<answer>yes</answer>
	</question>
	<question>
		<input>dad2</input>
		<input>dada12</input>
		<taskoptions></taskoptions>
		<answer>no</answer>
	</question>
	<question>
		<input>dca3</input>
		<input>dsad12</input>
		<taskoptions></taskoptions>
		<answer>no</answer>
	</question>
	<question>
		<input>fae</input>
		<input>weqed</input>
		<taskoptions></taskoptions>
		<answer>yes</answer>
	</question>
</taskFile>
