{"results":[{"type":"entry","task":{"name":"graphExpertise","question":"Do you have any expertise with network or graph visualizations?","description":"Do you have any expertise with network or graph visualizations?","inputs":[],"answer":{"type":"Options(fixed)","options":["No","Yes, with both.","Yes, with adjacency matrices","Yes, with node link diagrams"],"correctness":"no"}},"taskInstance":{},"response":"No","accuracy":-1.0,"group":"0_nodeLink,graph1,nodeCount;nodeLink,graph1,edgeCount;nodeLink,graph1,mostConnected;nodeLink,graph1,findNode;nodeLink,graph1,findLink;nodeLink,graph1,findNeighbor;nodeLink,graph1,findPath;nodeLink,graph2,nodeCount;nodeLink,graph2,edgeCount;nodeLink,graph2,mostConnected;nodeLink,graph2,findNode;nodeLink,graph2,findLink;nodeLink,graph2,findNeighbor;nodeLink,graph2,findPath;nodeLink,graph4,nodeCount;nodeLink,graph4,edgeCount;nodeLink,graph4,mostConnected;nodeLink,graph4,findNode;nodeLink,graph4,findLink;nodeLink,graph4,findNeighbor;nodeLink,graph4,findPath;adjecencyMatrix,graph1,nodeCount;adjecencyMatrix,graph1,edgeCount;adjecencyMatrix,graph1,mostConnected;adjecencyMatrix,graph1,findNode;adjecencyMatrix,graph1,findLink;adjecencyMatrix,graph1,findNeighbor;adjecencyMatrix,graph1,findPath;adjecencyMatrix,graph2,nodeCount;adjecencyMatrix,graph2,edgeCount;adjecencyMatrix,graph2,mostConnected;adjecencyMatrix,graph2,findNode;adjecencyMatrix,graph2,findLink;adjecencyMatrix,graph2,findNeighbor;adjecencyMatrix,graph2,findPath;adjecencyMatrix,graph4,nodeCount;adjecencyMatrix,graph4,edgeCount;adjecencyMatrix,graph4,mostConnected;adjecencyMatrix,graph4,findNode;adjecencyMatrix,graph4,findLink;adjecencyMatrix,graph4,findNeighbor;adjecencyMatrix,graph4,findPath","time":1549}]}